AUTHORS.txt
CHANGES.txt
LICENSE.txt
MANIFEST.in
README.rst
setup.py
dop/__init__.py
dop/client.py
dop.egg-info/PKG-INFO
dop.egg-info/SOURCES.txt
dop.egg-info/dependency_links.txt
dop.egg-info/not-zip-safe
dop.egg-info/requires.txt
dop.egg-info/top_level.txt