Metadata-Version: 1.1
Name: dop
Version: 0.1.5
Summary: A Python client for the Digital Ocean API
Home-page: http://github.com/ahmontero/dop
Author: Antonio Hinojo
Author-email: hello@ahmontero.com
License: Copyright (c) 2013-2014 Antonio H Montero.
